sa_request/__init__.py
sa_request/exceptions.py
sa_request/helper.py
django_sa_request-0.9.1b0.dist-info/METADATA
django_sa_request-0.9.1b0.dist-info/WHEEL
django_sa_request-0.9.1b0.dist-info/top_level.txt
django_sa_request-0.9.1b0.dist-info/RECORD
