Metadata-Version: 2.1
Name: django-sa-request
Version: 0.9.1b0
Summary: Django Simple Processor
Home-page: https://github.com/sauditore/SARequest/
Author: Amir Pourjafari
Author-email: amir.pourjafari@gmail.com
License: UNKNOWN
Project-URL: Bug Tracker, https://github.com/sauditore/SARequest/issues
Platform: UNKNOWN
Classifier: Programming Language :: Python :: 3
Classifier: License :: OSI Approved :: MIT License
Classifier: Operating System :: OS Independent
Requires-Python: >=3.6
Requires-Dist: khayyam
Requires-Dist: django
